drowsy/__init__.py
drowsy/base.py
drowsy/convert.py
drowsy/exc.py
drowsy/fields.py
drowsy/log.py
drowsy/parser.py
drowsy/permissions.py
drowsy/query_builder.py
drowsy/resource.py
drowsy/resource_class_registry.py
drowsy/router.py
drowsy/schema.py
drowsy/utils.py
Drowsy-0.1.6.dist-info/METADATA
Drowsy-0.1.6.dist-info/WHEEL
Drowsy-0.1.6.dist-info/top_level.txt
Drowsy-0.1.6.dist-info/RECORD
